fraser_gehrig/__init__.py
fraser_gehrig/fraser_gehrig.py
fraser_gehrig-0.1.2.dist-info/LICENSE.md
fraser_gehrig-0.1.2.dist-info/METADATA
fraser_gehrig-0.1.2.dist-info/WHEEL
fraser_gehrig-0.1.2.dist-info/top_level.txt
fraser_gehrig-0.1.2.dist-info/RECORD
