Metadata-Version: 2.1
Name: fraser-gehrig
Version: 0.1.2
Summary: A package to scrape AFL data.
Author-email: Harry Goodman <harryfgoodman@gmail.com>, Gabriel Dennis <gabrieldennis17@gmail.com>
License: MIT
Requires-Python: >=3.8.1
License-File: LICENSE.md
Requires-Dist: pandas
Requires-Dist: requests
Requires-Dist: bs4
